.gitignore
LICENSE
MANIFEST.in
README.rst
_config.yml
requirements.txt
setup.py
docs/Makefile
docs/conf.py
docs/index.rst
docs/make.bat
docs/_static/css/newstyle.css
docs/source/tables.rst
docs/source/taurus.rst
docs/source/analysis/get_no_ring_pairs.rst
docs/source/analysis/solve_for_origins.rst
docs/source/data_journal/data_stash.rst
docs/source/data_journal/log_and_stash.rst
docs/source/data_journal/logged_function.rst
docs/source/intervening_opportunities/build_rings_from_layout.rst
docs/source/intervening_opportunities/build_uniform_rings.rst
docs/source/intervening_opportunities/build_weighted_rings.rst
docs/source/intervening_opportunities/convolution.rst
docs/source/intervening_opportunities/create_escape_fraction_selectivity.rst
docs/source/intervening_opportunities/destnation_shift.rst
docs/source/intervening_opportunities/general_shift.rst
docs/source/intervening_opportunities/get_max_distance.rst
docs/source/intervening_opportunities/import_model_parameters.rst
docs/source/intervening_opportunities/merge_ring_with_next.rst
docs/source/intervening_opportunities/motion_exchange.rst
docs/source/intervening_opportunities/normalize_motion_exchange.rst
docs/source/intervening_opportunities/only_origin_in_first_ring.rst
docs/source/intervening_opportunities/origins_shift.rst
docs/source/intervening_opportunities/read_rings_layout.rst
docs/source/intervening_opportunities/ring_total.rst
docs/source/intervening_opportunities/save_intopp_parameters.rst
docs/source/intervening_opportunities/save_model_parameters.rst
docs/source/intervening_opportunities/snap_outstanding_od_to_last_ring.rst
docs/source/modules/analysis.rst
docs/source/modules/data_journal.rst
docs/source/modules/intervening_opportunities.rst
docs/source/modules/mst.png
docs/source/modules/mst.rst
docs/source/modules/network_generator.rst
docs/source/modules/route.rst
docs/source/mst/minimum_spanning_tree_from_distance.rst
docs/source/mst/minimum_spanning_tree_from_network.rst
pankus.egg-info/PKG-INFO
pankus.egg-info/SOURCES.txt
pankus.egg-info/dependency_links.txt
pankus.egg-info/requires.txt
pankus.egg-info/top_level.txt
