Metadata-Version: 1.1
Name: pankus
Version: 3.1.1
Summary: Spatial planning software
Home-page: http://github.com/mk45/pankus
Author: UNKNOWN
Author-email: maciej.kaminski@pwr.edu.pl
License: (c) Politechnika Wrocławska
Platform: UNKNOWN
Classifier: Development Status :: 3 - Alpha
Classifier: Environment :: Console
Classifier: Intended Audience :: Science/Research
Classifier: License :: Free For Educational Use
Classifier: Programming Language :: Python :: 3
Classifier: Programming Language :: SQL
Classifier: Topic :: Scientific/Engineering :: GIS
